nuttel-0.0.1.data/scripts/nuttel.py
nuttel-0.0.1.dist-info/DESCRIPTION.rst
nuttel-0.0.1.dist-info/METADATA
nuttel-0.0.1.dist-info/RECORD
nuttel-0.0.1.dist-info/WHEEL
nuttel-0.0.1.dist-info/metadata.json
nuttel-0.0.1.dist-info/top_level.txt
tests/__init__.py
tests/test_sshun.py
