Metadata-Version: 2.0
Name: nuttel
Version: 0.0.1
Summary: SSH Tunnel Utilties
Home-page: https://github.com/brettbeeson/nuttel
Author: Brett Beeson
Author-email: brettbeeson@fastmail.com
License: UNKNOWN
Platform: UNKNOWN
Classifier: Programming Language :: Python :: 3
Classifier: License :: OSI Approved :: MIT License
Classifier: Operating System :: OS Independent
Requires-Python: >=3.6
Requires-Dist: psutil
Requires-Dist: sshconf
